{
  "all_chat_data": {
    "-1002718732381": {
      "player_stats": {
        "1599213796": {
          "username": "pussycat_1204",
          "score": 0,
          "wins": 0,
          "losses": 0,
          "last_active": "2025-06-16T23:11:37.030781"
        }
      },
      "match_counter": 2,
      "match_history": [],
      "group_admins": [
        1599213796,
        1176326151
      ],
      "consecutive_idle_matches": 0
    },
    "-1002780424700": {
      "player_stats": {
        "6809465186": {
          "username": "H",
          "score": 0,
          "wins": 0,
          "losses": 0,
          "last_active": "2025-06-17T11:04:18.878678"
        },
        "1599213796": {
          "username": "pussycat_1204",
          "score": 0,
          "wins": 0,
          "losses": 0,
          "last_active": "2025-06-17T11:05:02.604989"
        }
      },
      "match_counter": 1,
      "match_history": [],
      "group_admins": [],
      "consecutive_idle_matches": 0
    }
  },
  "admin_data": {
    "1599213796": {
      "username": "pussycat_1204",
      "chat_points": {
        "-1": {
          "points": 10000000,
          "last_refill": null
        },
        "-1002718732381": {
          "points": 10000000,
          "last_refill": "2025-06-16T16:40:04.403454+00:00"
        },
        "-1002689980361": {
          "points": 10000000,
          "last_refill": "2025-06-16T16:40:04.403583+00:00"
        },
        "-1002780424700": {
          "points": 9990000,
          "last_refill": "2025-06-16T16:43:08.099347+00:00"
        }
      }
    },
    "1176326151": {
      "username": "Unknown Admin",
      "chat_points": {
        "-1": {
          "points": 10000000,
          "last_refill": null
        },
        "-1002780424700": {
          "points": 10000000,
          "last_refill": "2025-06-16T16:43:08.099398+00:00"
        },
        "-1002718732381": {
          "points": 10000000,
          "last_refill": "2025-06-16T16:43:08.099421+00:00"
        },
        "-1002689980361": {
          "points": 10000000,
          "last_refill": "2025-06-16T16:43:08.099442+00:00"
        }
      }
    }
  },
  "global_user_data": {
    "1599213796": {
      "full_name": "Pussy cat 🐱",
      "username": "pussycat_1204",
      "referral_points": 0,
      "referred_by": null,
      "pending_referrer_id": null
    },
    "6809465186": {
      "full_name": "H",
      "username": "H",
      "referral_points": 0,
      "referred_by": null,
      "pending_referrer_id": null
    }
  }
}